addpage/__init__.py
addpage/__main__.py
addpage/py.typed
addpage-0.4.1.dist-info/METADATA
addpage-0.4.1.dist-info/WHEEL
addpage-0.4.1.dist-info/entry_points.txt
addpage-0.4.1.dist-info/licenses/LICENSE
addpage-0.4.1.dist-info/RECORD
