Metadata-Version: 2.3
Name: addpage
Version: 0.4.1
Summary: `addpage` is a package for adding page number to PDF file.
Project-URL: homepage, https://github.com/SaitoTsutomu/addpage
Author-email: Saito Tsutomu <tsutomu7@hotmail.co.jp>
License: Apache-2.0
License-File: LICENSE
Classifier: Development Status :: 1 - Planning
Classifier: License :: OSI Approved :: Apache Software License
Classifier: Programming Language :: Python
Classifier: Topic :: Scientific/Engineering
Classifier: Topic :: Software Development
Requires-Python: >=3.12
Requires-Dist: pdfformfiller>=0.4
Requires-Dist: pypdf2==1.27.9
Requires-Dist: reportlab>=4.2.4
